unbabel/__init__.py
unbabel/api.py
unbabel/xliff_converter.py
unbabel_py-0.49.dist-info/DESCRIPTION.rst
unbabel_py-0.49.dist-info/METADATA
unbabel_py-0.49.dist-info/RECORD
unbabel_py-0.49.dist-info/WHEEL
unbabel_py-0.49.dist-info/metadata.json
unbabel_py-0.49.dist-info/top_level.txt
