Metadata-Version: 2.0
Name: unbabel-py
Version: 0.49
Summary: Python Wrapper around Unbabel HTTP API
Home-page: https://github.com/Unbabel/unbabel-py
Author: Joao Graca
Author-email: joao@unbabel.com
License: UNKNOWN
Download-URL: https://github.com/Unbabel/unbabel-py/archive/0.49.tar.gz
Platform: UNKNOWN
Classifier: Development Status :: 4 - Beta
Classifier: Intended Audience :: Developers
Classifier: Programming Language :: Python 
Classifier: Topic :: Text Processing
Requires-Dist: beautifulsoup4
Requires-Dist: requests
